preprocess/__init__.py
preprocess/preprocessor.py
preprocess/data/__init__.py
preprocess/data/data.py
preprocess/utils/__init__.py
preprocess/utils/utils.py
medical_dataset_analyzer-0.0.1.dist-info/LICENSE
medical_dataset_analyzer-0.0.1.dist-info/METADATA
medical_dataset_analyzer-0.0.1.dist-info/WHEEL
medical_dataset_analyzer-0.0.1.dist-info/top_level.txt
medical_dataset_analyzer-0.0.1.dist-info/RECORD
